stacktracer.py
stacktracer-0.1.2.dist-info/DESCRIPTION.rst
stacktracer-0.1.2.dist-info/METADATA
stacktracer-0.1.2.dist-info/metadata.json
stacktracer-0.1.2.dist-info/pbr.json
stacktracer-0.1.2.dist-info/RECORD
stacktracer-0.1.2.dist-info/top_level.txt
stacktracer-0.1.2.dist-info/WHEEL
