Metadata-Version: 2.0
Name: stacktracer
Version: 0.1.2
Summary: Stack tracer for multi-threaded applications
Home-page: https://github.com/messense/stacktracer
Author: messense
Author-email: messense@icloud.com
License: UNKNOWN
Keywords: stack,tracer,multi-threaded,threading
Platform: UNKNOWN
Classifier: Development Status :: 4 - Beta
Classifier: License :: OSI Approved :: MIT License
Classifier: Operating System :: MacOS
Classifier: Operating System :: POSIX
Classifier: Operating System :: POSIX :: Linux
Classifier: Programming Language :: Python
Classifier: Programming Language :: Python :: Implementation :: CPython
Classifier: Intended Audience :: Developers
Classifier: Topic :: Software Development :: Libraries
Classifier: Topic :: Software Development :: Libraries :: Python Modules
Classifier: Topic :: Utilities
Requires-Dist: pygments
